[
    {
        "name":"Black Dress",
        "category":"women",
        "size": {
            "xs": 12,
            "s": 0,
            "m": 0,
            "l": 26,
            "xl": 37
            },
        "imageURL":"/images/products/womens/black_dress",
        "description":"Every closet needs a simple black dress and this one is perfect for any occassion. Soft spun silk with flattering cuts for any occassion makes this a must have item. ",
        "price":2600,
        "attribution":"Photo by Andrea Piacquadio",
        "care":"For best results, dry clean only."
    },
    {
        "name":"Blue Flowers",
        "category":"women",
        "size": {
            "xs": 2,
            "s": 33,
            "m": 5,
            "l": 0,
            "xl":27
            },
        "imageURL":"/images/products/womens/blue_flowers",
        "description":"Playful flowers adorn this take on Boho Chic with a 100% cotton dress fit for any occassion.  ",
        "price":3400,
        "attribution":"Photo by Henry de Guzman",
        "care":"For best results, dry clean only. Machine washable on cold. Do not tumble dry. Hang or lay flat to dry."
    },
    {
        "name":"Casual Linen",
        "category":"women",
        "size": {
            "xs": 2,
            "s": 0,
            "m": 1,
            "l": 36,
            "xl": 27
            },
        "imageURL":"/images/products/womens/casual",
        "description":"Casual and comfortable linen makes this outfit one to live for. The loose fit and easy wear makes this a neccessary part of any wardrobe.",
        "price":2350,
        "attribution":"Photo by Piril Şahin",
        "care":"For best results, dry clean only. Machine washable on cold. Do not tumble dry. Hang or lay flat to dry."
    },
    {
        "name":"Copper Sequin",
        "category":"women",
        "size": {
            "xs": 0,
            "s": 0,
            "m": 45,
            "l": 26,
            "xl": 0
            },
        "imageURL":"/images/products/womens/copper_sequin",
        "description":"Your night on the town will be unforgetable with this in your closet. This dress will catch the lights and the attention whether it's on the dance floor or at dinner.",
        "price":5670,
        "attribution":"Photo by Andrea Piacquadio",
        "care":"For best results, dry clean only. "
    },
    {
        "name":"Gold Dress",
        "category":"women",
        "size": {
            "xs": 2,
            "s": 3,
            "m": 5,
            "l": 6,
            "xl": 7
            },
        "imageURL":"/images/products/womens/gold_dress",
        "description":"Elegance and Haute Couture meet in this spectacular piece of wearable art. 100% breathable cotton is the base of this statement piece that will leave those around you breathless.",
        "price":16800,
        "attribution":"Photo by CENGIZ AKTURK",
        "care":"For best results, dry clean only. Machine washable on cold. Do not tumble dry. Hang to dry."
    },
    {
        "name":"Lemon Yellow Dress",
        "category":"women",
        "size": {
            "xs": 10,
            "s": 35,
            "m": 5,
            "l": 26,
            "xl": 1
            },
        "imageURL":"/images/products/womens/lemon_yellow",
        "description":"Take the sundress to the next level with this bright lemon yellow dress that looks just as spectacular on the beach as it does on the town.",
        "price":2580,
        "attribution":"Photo by CENGIZ AKTURK",
        "care":"For best results, dry clean only. Machine washable on cold. Do not tumble dry. Hang to dry."
    },
    {
        "name":"Print Dress",
        "category":"women",
        "size": {
            "xs": 22,
            "s": 13,
            "m": 55,
            "l": 6,
            "xl": 7
            },
        "imageURL":"/images/products/womens/print",
        "description":"This stylish print takes this simple dress from good to fantastic. 100% cotton is easy to wear and care for while still turning heads.",
        "price":4560,
        "attribution":"Photo by Jame_9bkk",
        "care":"For best results, dry clean only. Machine washable on cold. Do not tumble dry. Lay flat to dry."
    },
    {
        "name":"Silver Sequin",
        "category":"women",
        "size": {
            "xs": 23,
            "s": 53,
            "m": 35,
            "l": 6,
            "xl": 7
            },
        "imageURL":"/images/products/womens/sequin_with_fur",
        "description":"Silver sequins are classy, elegant, and exciting in this dress made for nights on the town ",
        "price":4500,
        "attribution":"Photo by Olcay Ertem",
        "care":"For best results, dry clean only. "
    },
    {
        "name":"Silver Dress",
        "category":"women",
        "size": {
            "xs": 22,
            "s": 31,
            "m": 5,
            "l": 0,
            "xl": 7
            },
        "imageURL":"/images/products/womens/silver_dress",
        "description":"Silve lamme has never looked better in this amazing new addition to our lineup. Expertly crafted and guaranteed to fit to perfection.",
        "price":15300,
        "attribution":"Photo by CENGIZ AKTURK",
        "care":"For best results, dry clean only. "
    },
    {
        "name":"White Dress",
        "category":"women",
        "size": {
            "xs": 2,
            "s": 3,
            "m": 5,
            "l": 6,
            "xl": 1
            },
        "imageURL":"/images/products/womens/white_dress",
        "description":"Elegance meets otherworldly fashion in this fabulous white dress. Made of 100% cotton, this dress will never fail to impress.",
        "price":23300,
        "attribution":"Photo by Tuấn Kiệt Jr.",
        "care":"For best results, dry clean only. Machine washable on cold. Do not tumble dry. Hang or lay flat to dry."
    }
]